[
  { "id": "s1",  "clientId": "cl1", "name": "Next – Luton The Mall",                  "address": "Bute Street, Luton",                   "postcode": "LU1 2TL", "type": "Retail",       "currentCleaner": "c3",  "slaWindow": "06:00–08:00", "contract": 1800 },
  { "id": "s2",  "clientId": "cl1", "name": "Next – Centre:MK",                        "address": "Silbury Arcade, Milton Keynes",         "postcode": "MK9 3EB", "type": "Retail",       "currentCleaner": "c20", "slaWindow": "06:00–08:30", "contract": 2400 },
  { "id": "s3",  "clientId": "cl1", "name": "Next – Watford Atria",                    "address": "The Atria, Watford",                   "postcode": "WD17 1NJ","type": "Retail",       "currentCleaner": "c11", "slaWindow": "07:30–08:30", "contract": 900 },
  { "id": "s4",  "clientId": "cl2", "name": "L&D Hospital – Main Tower",               "address": "Lewsey Road, Luton",                   "postcode": "LU4 0DZ", "type": "Healthcare",   "currentCleaner": "c29", "slaWindow": "05:00–07:00", "contract": 6500 },
  { "id": "s5",  "clientId": "cl2", "name": "L&D Hospital – A&E & Outpatients",        "address": "Lewsey Road, Luton",                   "postcode": "LU4 0DZ", "type": "Healthcare",   "currentCleaner": "c21", "slaWindow": "05:30–07:30", "contract": 3200 },
  { "id": "s6",  "clientId": "cl3", "name": "Aldi – Dunstable Distribution RDC",       "address": "Woodside Industrial Estate, Dunstable", "postcode": "LU5 4TP", "type": "Industrial",   "currentCleaner": "c10", "slaWindow": "04:00–07:00", "contract": 4200 },
  { "id": "s7",  "clientId": "cl4", "name": "Waterstones – Watford",                   "address": "Charter Place, Watford",               "postcode": "WD17 2RT","type": "Retail",       "currentCleaner": "c13", "slaWindow": "06:00–09:00", "contract": 2100 },
  { "id": "s8",  "clientId": "cl5", "name": "Luton Town Hall",                         "address": "Town Hall Square, Luton",              "postcode": "LU1 2BQ", "type": "Government",   "currentCleaner": "c1",  "slaWindow": "06:00–08:00", "contract": 2800 },
  { "id": "s9",  "clientId": "cl5", "name": "Luton Customer Service Centre",           "address": "George Street West, Luton",            "postcode": "LU1 2ND", "type": "Government",   "currentCleaner": "c17", "slaWindow": "06:00–08:00", "contract": 2200 },
  { "id": "s10", "clientId": "cl6", "name": "University of Bedfordshire – Luton Campus","address": "Park Square, Luton",                  "postcode": "LU1 3JU", "type": "Education",    "currentCleaner": "c15", "slaWindow": "07:00–09:00", "contract": 3500 },
  { "id": "s11", "clientId": "cl7", "name": "Premier Inn Luton Airport",               "address": "2 Percival Way, Luton",                "postcode": "LU2 9GP", "type": "Hospitality",  "currentCleaner": "c9",  "slaWindow": "08:00–14:00", "contract": 1800 },
  { "id": "s12", "clientId": "cl8", "name": "Central Bedfordshire Council HQ",         "address": "Priory House, Monks Walk, Shefford",   "postcode": "SG17 5TQ","type": "Government",   "currentCleaner": "c24", "slaWindow": "06:00–08:00", "contract": 2600 },
  { "id": "s13", "clientId": "cl5", "name": "Luton Central Library",                   "address": "St George's Square, Luton",            "postcode": "LU1 2NG", "type": "Government",   "currentCleaner": "c5",  "slaWindow": "07:00–08:00", "contract": 1100 },
  { "id": "s14", "clientId": "cl6", "name": "University of Bedfordshire – Bedford Campus","address": "Polhill Avenue, Bedford",            "postcode": "MK41 9EA","type": "Education",    "currentCleaner": "c9",  "slaWindow": "07:00–09:00", "contract": 2900 },
  { "id": "s15", "clientId": "cl8", "name": "Central Bedfordshire – Watling House",    "address": "High Street South, Dunstable",         "postcode": "LU6 3JF", "type": "Government",   "currentCleaner": "c6",  "slaWindow": "06:00–08:00", "contract": 1400 }
]
